truenas_mcp_server/__init__.py
truenas_mcp_server/exceptions.py
truenas_mcp_server/server.py
truenas_mcp_server/client/__init__.py
truenas_mcp_server/client/http_client.py
truenas_mcp_server/config/__init__.py
truenas_mcp_server/config/settings.py
truenas_mcp_server/models/__init__.py
truenas_mcp_server/models/base.py
truenas_mcp_server/models/sharing.py
truenas_mcp_server/models/storage.py
truenas_mcp_server/models/user.py
truenas_mcp_server/tools/__init__.py
truenas_mcp_server/tools/base.py
truenas_mcp_server/tools/debug.py
truenas_mcp_server/tools/sharing.py
truenas_mcp_server/tools/snapshots.py
truenas_mcp_server/tools/storage.py
truenas_mcp_server/tools/users.py
truenas_mcp_server-3.0.2.dist-info/licenses/LICENSE
truenas_mcp_server-3.0.2.dist-info/METADATA
truenas_mcp_server-3.0.2.dist-info/WHEEL
truenas_mcp_server-3.0.2.dist-info/entry_points.txt
truenas_mcp_server-3.0.2.dist-info/top_level.txt
truenas_mcp_server-3.0.2.dist-info/RECORD
