Metadata-Version: 2.4
Name: truenas-mcp-server
Version: 3.0.2
Summary: Production-ready MCP server for TrueNAS Core - Control your NAS through natural language
Home-page: https://github.com/vespo92/TrueNasCoreMCP
Author: Vinnie Espo
Author-email: Vinnie Espo <vespo92@gmail.com>
License: MIT
Project-URL: Homepage, https://github.com/vespo92/TrueNasCoreMCP
Project-URL: Documentation, https://github.com/vespo92/TrueNasCoreMCP/wiki
Project-URL: Repository, https://github.com/vespo92/TrueNasCoreMCP.git
Project-URL: Issues, https://github.com/vespo92/TrueNasCoreMCP/issues
Project-URL: Changelog, https://github.com/vespo92/TrueNasCoreMCP/blob/main/CHANGELOG.md
Keywords: truenas,mcp,claude,api,nas,storage,zfs,smb,nfs,iscsi,kubernetes
Classifier: Development Status :: 4 - Beta
Classifier: Intended Audience :: System Administrators
Classifier: Intended Audience :: Developers
Classifier: Topic :: System :: Systems Administration
Classifier: Topic :: System :: Archiving :: Backup
Classifier: Topic :: System :: Filesystems
Classifier: Operating System :: OS Independent
Classifier: Programming Language :: Python :: 3
Classifier: Programming Language :: Python :: 3.10
Classifier: Programming Language :: Python :: 3.11
Classifier: Programming Language :: Python :: 3.12
Classifier: Framework :: AsyncIO
Requires-Python: >=3.10
License-File: LICENSE
Requires-Dist: mcp>=1.1.0
Requires-Dist: httpx>=0.27.0
Requires-Dist: python-dotenv>=1.0.0
Requires-Dist: pydantic>=2.0.0
Requires-Dist: pydantic-settings>=2.0.0
Provides-Extra: dev
Requires-Dist: pytest>=7.0.0; extra == "dev"
Requires-Dist: pytest-asyncio>=0.21.0; extra == "dev"
Requires-Dist: pytest-cov>=4.0.0; extra == "dev"
Requires-Dist: pytest-mock>=3.10.0; extra == "dev"
Requires-Dist: black>=23.0.0; extra == "dev"
Requires-Dist: flake8>=6.0.0; extra == "dev"
Requires-Dist: flake8-docstrings>=1.7.0; extra == "dev"
Requires-Dist: mypy>=1.0.0; extra == "dev"
Requires-Dist: isort>=5.12.0; extra == "dev"
Requires-Dist: pre-commit>=3.0.0; extra == "dev"
Requires-Dist: safety>=2.3.0; extra == "dev"
Requires-Dist: bandit>=1.7.5; extra == "dev"
Provides-Extra: docs
Requires-Dist: mkdocs>=1.5.0; extra == "docs"
Requires-Dist: mkdocs-material>=9.0.0; extra == "docs"
Requires-Dist: mkdocstrings[python]>=0.24.0; extra == "docs"
Dynamic: author
Dynamic: home-page
Dynamic: license-file
Dynamic: requires-python
